[{"family":"MaterialIcons","fonts":[{"asset":"fonts/MaterialIcons-Regular.otf"}]},{"family":"AttackOfMonster","fonts":[{"asset":"fonts/Attack-Of-Monster.ttf"}]},{"family":"Merriweather","fonts":[{"asset":"fonts/Merriweather-Black.ttf"},{"asset":"fonts/Merriweather-BlackItalic.ttf"},{"asset":"fonts/Merriweather-Bold.ttf"},{"asset":"fonts/Merriweather-BoldItalic.ttf"},{"asset":"fonts/Merriweather-Italic.ttf"},{"asset":"fonts/Merriweather-Light.ttf"},{"asset":"fonts/Merriweather-LightItalic.ttf"},{"asset":"fonts/Merriweather-Regular.ttf"}]},{"family":"packages/cupertino_icons/CupertinoIcons","fonts":[{"asset":"packages/cupertino_icons/assets/CupertinoIcons.ttf"}]}]